{
  "generatedAt": "2026-06-27T05:49:46.897Z",
  "note": "Seed backfill compiled from major public AVSEC events Jul 2025 - May 2026. Best-effort major-event reconstruction, thinner than the live daily pull. The daily Action accumulates fresh data from here.",
  "days": [
    {
      "date": "2025-07-15",
      "briefing": "Scattered Spider's social-engineering campaign sweeps global aviation, hitting carriers across three continents; analysts warn cyberattacks on the sector have surged sharply year-on-year.",
      "items": [
        {
          "title": "Qantas breach exposes up to 6M customer records",
          "category": "Incident",
          "region": "Asia-Pacific",
          "severity": "High",
          "summary": "Scattered Spider suspected in a breach exposing personal data of up to six million Qantas customers via a third party.",
          "source": "Help Net Security",
          "url": "https://www.helpnetsecurity.com/2025/07/21/aviation-industry-cybersecurity-crisis/",
          "date": "2025-07-02"
        },
        {
          "title": "Scattered Spider hits WestJet and Hawaiian Airlines",
          "category": "Incident",
          "region": "North America",
          "severity": "High",
          "summary": "Coordinated social-engineering attacks disrupted internal systems and apps at North American carriers.",
          "source": "Aerospace Global News",
          "url": "https://aerospaceglobalnews.com/news/airline-airport-aviation-cyberattacks-2025/",
          "date": "2025-06-13"
        },
        {
          "title": "Air France-KLM third-party platform breached",
          "category": "Incident",
          "region": "Europe",
          "severity": "Medium",
          "summary": "Unauthorised activity detected on an external customer-service platform used by the carriers.",
          "source": "Aerospace Global News",
          "url": "https://aerospaceglobalnews.com/news/airline-airport-aviation-cyberattacks-2025/",
          "date": "2025-07-10"
        },
        {
          "title": "Thales: aviation cyberattacks up ~600%",
          "category": "Threat",
          "region": "Europe",
          "severity": "Medium",
          "summary": "Thales reported aviation cyberattacks rose roughly 600 percent year-on-year, with dozens of ransomware incidents logged.",
          "source": "Help Net Security",
          "url": "https://www.helpnetsecurity.com/2025/07/21/aviation-industry-cybersecurity-crisis/",
          "date": "2025-07-21"
        }
      ]
    },
    {
      "date": "2025-08-15",
      "briefing": "A quieter month for incidents but heavy on rule-making: regulators on both sides of the Atlantic tighten aviation cyber obligations.",
      "items": [
        {
          "title": "TSA issues aviation cybersecurity amendments",
          "category": "Regulatory",
          "region": "North America",
          "severity": "Medium",
          "summary": "TSA rolled out amendments mandating stronger cyber controls and incident-reporting protocols for the aviation sector.",
          "source": "Breached.Company",
          "url": "https://breached.company/aviation-under-siege-the-2025-airline-and-airport-cyberattack-crisis/",
          "date": "2025-08-10"
        },
        {
          "title": "EASA Part-IS information-security rules near deadline",
          "category": "Regulatory",
          "region": "Europe",
          "severity": "Medium",
          "summary": "EASA Part-IS requirements extend information-security duties to airlines, airports and ANSPs with phased deadlines into 2026.",
          "source": "Help Net Security",
          "url": "https://www.helpnetsecurity.com/2025/07/21/aviation-industry-cybersecurity-crisis/",
          "date": "2025-08-12"
        },
        {
          "title": "ICAO advances Cybersecurity Action Plan",
          "category": "Regulatory",
          "region": "North America",
          "severity": "Low",
          "summary": "ICAO pushed its Cybersecurity Action Plan focusing on governance, faster incident response and security-by-design.",
          "source": "Help Net Security",
          "url": "https://www.helpnetsecurity.com/2025/07/21/aviation-industry-cybersecurity-crisis/",
          "date": "2025-08-20"
        }
      ]
    },
    {
      "date": "2025-09-19",
      "briefing": "Europe's worst aviation security week in years: a supply-chain ransomware attack paralyses major-hub check-in while a wave of airport drone incursions triggers hybrid-threat fears.",
      "items": [
        {
          "title": "Collins Aerospace MUSE ransomware grounds check-in",
          "category": "Incident",
          "region": "Europe",
          "severity": "High",
          "summary": "HardBit ransomware crippled the Collins MUSE check-in platform, forcing manual processing at Heathrow, Brussels, Berlin and Dublin.",
          "source": "Wikipedia",
          "url": "https://en.wikipedia.org/wiki/Collins_Aerospace_cyberattack",
          "date": "2025-09-19"
        },
        {
          "title": "Copenhagen and Oslo airports shut by drones",
          "category": "Incident",
          "region": "Europe",
          "severity": "High",
          "summary": "Large drones forced a four-hour Copenhagen shutdown and a brief Oslo closure; Denmark called it a hybrid attack on critical infrastructure.",
          "source": "CNN",
          "url": "https://www.cnn.com/2025/09/25/world/drones-denmark-hybrid-attack-wwk-intl",
          "date": "2025-09-22"
        },
        {
          "title": "Wave of drone closures across Danish airports",
          "category": "Incident",
          "region": "Europe",
          "severity": "High",
          "summary": "Repeated sightings closed Aalborg, Billund and other Danish airports over several nights, with military sites also affected.",
          "source": "Euronews",
          "url": "https://www.euronews.com/my-europe/2025/11/20/fact-checking-europes-drone-problem-why-are-airports-shuttering-over-drone-sightings",
          "date": "2025-09-25"
        },
        {
          "title": "ENISA confirms airport outage was ransomware",
          "category": "Regulatory",
          "region": "Europe",
          "severity": "Medium",
          "summary": "The EU cyber agency ENISA confirmed the Collins airport disruption as a ransomware attack and opened investigations.",
          "source": "Security Affairs",
          "url": "https://securityaffairs.com/182363/hacking/a-cyberattack-on-collins-aerospace-disrupted-operations-at-major-european-airports.html",
          "date": "2025-09-22"
        }
      ]
    },
    {
      "date": "2025-10-15",
      "briefing": "The drone disruption spreads south and west across Europe; governments increasingly frame the incursions as state-linked hybrid activity.",
      "items": [
        {
          "title": "Munich Airport suspends flights twice over drones",
          "category": "Incident",
          "region": "Europe",
          "severity": "High",
          "summary": "Munich halted operations twice within 24 hours over drone sightings, stranding thousands of passengers.",
          "source": "Wikipedia",
          "url": "https://en.wikipedia.org/wiki/2025_European_drone_sightings",
          "date": "2025-10-03"
        },
        {
          "title": "Brussels and Liege airports closed by drones",
          "category": "Incident",
          "region": "Europe",
          "severity": "High",
          "summary": "Belgian airports briefly closed amid sightings; drones also seen over military bases and a nuclear plant.",
          "source": "Wikipedia",
          "url": "https://en.wikipedia.org/wiki/2025_European_drone_sightings",
          "date": "2025-10-20"
        },
        {
          "title": "Germany assesses drones as likely Russian espionage",
          "category": "Threat",
          "region": "Europe",
          "severity": "High",
          "summary": "German officials judged many overflights as probable state-linked espionage aimed at unsettling the public.",
          "source": "Euronews",
          "url": "https://www.euronews.com/my-europe/2025/11/20/fact-checking-europes-drone-problem-why-are-airports-shuttering-over-drone-sightings",
          "date": "2025-10-06"
        }
      ]
    },
    {
      "date": "2025-11-15",
      "briefing": "Counter-drone response moves from improvisation to coordination, with allied deployments in Europe and a US legal-authority push.",
      "items": [
        {
          "title": "Allies send counter-drone help to Belgium",
          "category": "Incident",
          "region": "Europe",
          "severity": "High",
          "summary": "Near-daily incursions over Belgian airports and bases prompted UK, France and Germany to deploy counter-drone support.",
          "source": "Euronews",
          "url": "https://www.euronews.com/my-europe/2025/11/20/fact-checking-europes-drone-problem-why-are-airports-shuttering-over-drone-sightings",
          "date": "2025-11-09"
        },
        {
          "title": "US drone incursions near airports up 25%+",
          "category": "Regulatory",
          "region": "North America",
          "severity": "Medium",
          "summary": "FAA data showed a sharp rise in airport drone incursions, intensifying the counter-UAS authority debate in Congress.",
          "source": "DroneUp",
          "url": "https://www.droneup.com/news/congressional-hearing",
          "date": "2025-11-21"
        }
      ]
    },
    {
      "date": "2025-12-15",
      "briefing": "Year-end sees authorities hard-coding the autumn drone lessons into temporary bans and broader take-down powers.",
      "items": [
        {
          "title": "Denmark and EU impose drone bans around summits",
          "category": "Regulatory",
          "region": "Europe",
          "severity": "Medium",
          "summary": "Temporary civilian drone bans were placed around airports and critical sites during high-profile EU events.",
          "source": "Al Jazeera",
          "url": "https://www.aljazeera.com/news/2025/9/28/denmark-bans-drone-flights-after-latest-drone-sightings-at-military-bases",
          "date": "2025-12-05"
        },
        {
          "title": "US expands counter-UAS take-down authority",
          "category": "Regulatory",
          "region": "North America",
          "severity": "Medium",
          "summary": "Congress moved to let more federal, state and local agencies disable rogue drones, subject to training.",
          "source": "NPR",
          "url": "https://www.npr.org/2026/02/27/g-s1-111794/lawmakers-say-us-military-used-laser-to-take-down-border-protection-drone",
          "date": "2025-12-18"
        }
      ]
    },
    {
      "date": "2026-01-15",
      "briefing": "The new year opens with drones firmly reframed from nuisance to national-security and business-continuity risk.",
      "items": [
        {
          "title": "Cartel border drones reframed as security threat",
          "category": "Threat",
          "region": "North America",
          "severity": "Medium",
          "summary": "Washington's terrorist designation of cartels recast persistent border drone activity as a national-security matter.",
          "source": "Fox News",
          "url": "https://www.foxnews.com/opinion/border-airspace-breached-cartel-drones-test-us-defenses-raise-new-fears",
          "date": "2026-01-12"
        },
        {
          "title": "2026 outlook: drones as a repeatable disruption tactic",
          "category": "Threat",
          "region": "North America",
          "severity": "Low",
          "summary": "Analysts warned drone incursions now behave like a low-cost, repeatable business-interruption tactic against critical sites.",
          "source": "DroneShield",
          "url": "https://www.droneshield.com/blog/the-new-airspace-risk-what-security-teams-need-to-know-about-drone-threats-2026",
          "date": "2026-01-20"
        }
      ]
    },
    {
      "date": "2026-02-11",
      "briefing": "Interagency miscoordination over counter-drone lasers shuts a major US airport twice in a month, the most disruptive domestic airspace closures since 9/11.",
      "items": [
        {
          "title": "FAA abruptly shuts El Paso airspace, then reverses",
          "category": "Incident",
          "region": "North America",
          "severity": "High",
          "summary": "The FAA grounded El Paso flights for a stated 10 days then lifted it hours later, tied to a counter-drone laser test near Fort Bliss.",
          "source": "CNBC",
          "url": "https://www.cnbc.com/2026/02/11/faa-el-paso-airport.html",
          "date": "2026-02-11"
        },
        {
          "title": "Second laser incident closes El Paso airspace again",
          "category": "Incident",
          "region": "North America",
          "severity": "High",
          "summary": "Two weeks later the military downed a CBP drone with a laser, prompting another El Paso closure and congressional criticism.",
          "source": "NPR",
          "url": "https://www.npr.org/2026/02/27/g-s1-111794/lawmakers-say-us-military-used-laser-to-take-down-border-protection-drone",
          "date": "2026-02-26"
        }
      ]
    },
    {
      "date": "2026-03-15",
      "briefing": "A quieter month dominated by follow-through: regulators press supply-chain resilience after the autumn ransomware shock.",
      "items": [
        {
          "title": "Post-Collins aviation supply-chain resilience review",
          "category": "Regulatory",
          "region": "Europe",
          "severity": "Low",
          "summary": "Reviews pushed EU supply-chain resilience and NIS2-aligned incident-reporting expectations for aviation technology vendors.",
          "source": "Wikipedia",
          "url": "https://en.wikipedia.org/wiki/Collins_Aerospace_cyberattack",
          "date": "2026-03-15"
        }
      ]
    },
    {
      "date": "2026-05-08",
      "briefing": "A fatal perimeter breach at a major US hub puts airfield intrusion and perimeter integrity back in the spotlight.",
      "items": [
        {
          "title": "Denver airport perimeter breach fatality",
          "category": "Incident",
          "region": "North America",
          "severity": "High",
          "summary": "A man breached Denver International's perimeter and was killed on a runway as a jet took off, reviving scrutiny of perimeter security.",
          "source": "ASIS Security Management",
          "url": "https://www.asisonline.org/security-management-magazine/latest-news/today-in-security/2026/may/denver-airport-breach/",
          "date": "2026-05-08"
        }
      ]
    },
    {
      "date": "2026-06-24",
      "briefing": "Global aviation security remains under significant pressure in mid-2026, with GPS spoofing attacks targeting Indian airports, a fatal perimeter breach at Denver International, and persistent cyber threats against aviation supply chains dominating the threat landscape. Regulatory activity is intensifying, with the FAA advancing long-delayed counter-UAS rulemaking, EASA's Part-IS cybersecurity mandate now fully in force, and ICAO's 2026-2028 Global Aviation Security Plan directing new work on weaponised UAS and GNSS interference.",
      "items": [
        {
          "title": "GPS Spoofing Cyberattack Hits Seven Major Indian Airports",
          "category": "Incident",
          "region": "Asia-Pacific",
          "severity": "High",
          "summary": "India confirmed GPS spoofing at seven airports including Delhi, Mumbai and Bengaluru, delivering false navigation data during landing; no flights cancelled.",
          "source": "Bright Defense / Financial Express",
          "url": "https://www.brightdefense.com/resources/recent-data-breaches/",
          "date": "2026-06-01"
        },
        {
          "title": "Fatal Perimeter Breach at Denver International Airport Triggers Security Review",
          "category": "Incident",
          "region": "North America",
          "severity": "High",
          "summary": "A man breached Denver Airport's perimeter on 8 May and was killed on an active runway, exposing critical perimeter security gaps.",
          "source": "ASIS Security Management / Associated Press",
          "url": "https://www.asisonline.org/security-management-magazine/latest-news/today-in-security/2026/may/denver-airport-breach/",
          "date": "2026-05-15"
        },
        {
          "title": "FAA Publishes Long-Awaited NPRM for Drone Flight Restrictions Over Critical Infrastructure",
          "category": "Regulatory",
          "region": "North America",
          "severity": "Medium",
          "summary": "FAA's Section 2209 NPRM, published 6 May 2026, establishes drone flight restriction zones over critical facilities; comments due 6 July 2026.",
          "source": "Holland & Knight",
          "url": "https://www.hklaw.com/en/insights/publications/2026/05/citing-national-security-needs-the-fcc-and-faa-take-steps-on-uas",
          "date": "2026-05-12"
        },
        {
          "title": "Aviation Booking Software Provider Breached in MFA-Fatigue Phishing Campaign",
          "category": "Incident",
          "region": "North America",
          "severity": "High",
          "summary": "March 2026 phishing attack compromised an airline booking software provider's IT admin credentials via MFA fatigue, exposing cloud and OT systems.",
          "source": "HALOCK Security Labs",
          "url": "https://www.halock.com/top-cyber-threats-in-the-aviation-sector/",
          "date": "2026-03-01"
        },
        {
          "title": "ICAO 2026–2028 Global Aviation Security Plan Targets Weaponised UAS and GNSS Threats",
          "category": "Regulatory",
          "region": "Asia-Pacific",
          "severity": "Medium",
          "summary": "ICAO Assembly adopted the Second Edition Global Aviation Security Plan, directing new work programme on weaponised UAS and GNSS radio frequency interference.",
          "source": "ICAO Newsroom",
          "url": "https://www.icao.int/news/icao-enhances-global-aviation-safety-and-security-framework",
          "date": "2025-10-03"
        },
        {
          "title": "EASA Part-IS Information Security Mandate Now Fully Binding Across EU Aviation",
          "category": "Regulatory",
          "region": "Europe",
          "severity": "Medium",
          "summary": "EASA Part-IS cybersecurity regulation became fully applicable as of February 2026, covering airlines, airports, MROs and ATC with mandatory ISMS requirements.",
          "source": "EASA / Airbus Protect",
          "url": "https://www.easa.europa.eu/en/the-agency/faqs/information-security-part",
          "date": "2026-02-22"
        }
      ]
    },
    {
      "date": "2026-06-25",
      "briefing": "Global aviation security faces a high-tempo threat environment driven by escalating GPS/GNSS spoofing campaigns targeting multiple countries, a sustained wave of cyber intrusions against airline and airport IT infrastructure, and fresh physical disruptions to critical airport facilities. Regulatory bodies including EASA, FAA, and ICAO are actively issuing conflict-zone bulletins, UAS restriction frameworks, and mandatory cybersecurity compliance deadlines in response to these converging threats.",
      "items": [
        {
          "title": "Caracas Simón Bolívar Airport Shut Down After Earthquake Destroys Terminal",
          "category": "Incident",
          "region": "Latin America",
          "severity": "High",
          "summary": "Twin earthquakes caused severe structural damage to Venezuela's main international gateway, suspending all flights pending full safety inspections of screening areas and infrastructure.",
          "source": "AirLive",
          "url": "https://airlive.net/news/2026/06/25/breaking-caracas-airport-shut-down-after-twin-earthquakes-devastate-venezuela/",
          "date": "2026-06-25"
        },
        {
          "title": "EASA Issues New Conflict Zone Bulletin on Iran, Iraq and Lebanon Airspace",
          "category": "Regulatory",
          "region": "Middle East",
          "severity": "High",
          "summary": "EASA CZIB 2026-03-R12 directs operators to avoid Iran, Iraq and Lebanon airspace and exercise caution across Bahrain, Israel, Jordan, Kuwait, Qatar, UAE, Oman and Saudi Arabia.",
          "source": "Safe Airspace / EASA",
          "url": "https://safeairspace.net/summary/",
          "date": "2026-06-10"
        },
        {
          "title": "FAA Publishes Long-Awaited NPRM to Restrict Drone Flights Over Critical Infrastructure",
          "category": "Regulatory",
          "region": "North America",
          "severity": "Medium",
          "summary": "FAA's Section 2209 NPRM establishes a process for facility owners to apply for UAS flight restrictions; public comment period closes 6 July 2026.",
          "source": "Holland & Knight / Federal Register",
          "url": "https://www.hklaw.com/en/insights/publications/2026/05/citing-national-security-needs-the-fcc-and-faa-take-steps-on-uas",
          "date": "2026-05-06"
        },
        {
          "title": "Aviation Booking Software Provider Hit by MFA-Fatigue Phishing Attack Affecting Multiple Airlines",
          "category": "Incident",
          "region": "North America",
          "severity": "High",
          "summary": "Threat actors used social engineering and MFA fatigue to compromise an IT administrator's credentials, gaining access to identity systems, Microsoft 365 and OT environments.",
          "source": "HALOCK Security Labs",
          "url": "https://www.halock.com/top-cyber-threats-in-the-aviation-sector/",
          "date": "2026-03-01"
        },
        {
          "title": "EASA Part-IS Information Security Implementing Regulation Now Fully Applicable",
          "category": "Regulatory",
          "region": "Europe",
          "severity": "Medium",
          "summary": "EASA's Part-IS cybersecurity rule became fully applicable on 22 February 2026, mandating Information Security Management Systems for airlines, airports, MROs and air navigation service providers.",
          "source": "EASA",
          "url": "https://www.easa.europa.eu/en/the-agency/faqs/information-security-part",
          "date": "2026-02-22"
        },
        {
          "title": "India Confirms Coordinated GPS Spoofing Campaign Targeting Eight Major Airports",
          "category": "Threat",
          "region": "Asia-Pacific",
          "severity": "High",
          "summary": "India's Civil Aviation Minister confirmed GPS spoofing and GNSS jamming at Delhi, Mumbai, Kolkata, Amritsar, Hyderabad, Bengaluru and Chennai airports; source unattributed, state-sponsored actor suspected.",
          "source": "The Register / Daily Pioneer",
          "url": "https://www.theregister.com/2025/12/03/india_gps_spoofing/",
          "date": "2025-12-03"
        }
      ]
    },
    {
      "date": "2026-06-26",
      "briefing": "The global aviation security environment over the past 72 hours has been marked by a deadly JNIM terrorist assault on Niamey's international airport in Niger and confirmed GPS spoofing attacks across seven major Indian airports, underscoring persistent physical and cyber threats to civil aviation worldwide. Simultaneously, the EU Council circulated a new Aviation Security Strategy document on 19 June 2026, and the FAA's critical infrastructure drone-restriction rulemaking (NPRM) entered its public-comment phase, reflecting accelerating regulatory responses to evolving UAS and hybrid threats.",
      "items": [
        {
          "title": "JNIM Militants Storm Niamey International Airport; 13 Killed",
          "category": "Incident",
          "region": "Africa",
          "severity": "High",
          "summary": "Al-Qaeda-linked JNIM attacked Diori Hamani Airport on 18 Jun 2026, killing 13; 22 attackers killed, 20 arrested. Second airport attack in 2026.",
          "source": "Wikipedia / multiple newswires",
          "url": "https://en.wikipedia.org/wiki/June_2026_Diori_Hamani_International_Airport_attack",
          "date": "2026-06-18"
        },
        {
          "title": "GPS Spoofing Cyberattack Hits Seven Major Indian Airports",
          "category": "Incident",
          "region": "Asia-Pacific",
          "severity": "High",
          "summary": "India confirmed GPS spoofing at Delhi, Mumbai, Kolkata, Hyderabad and Bengaluru airports, feeding false navigation data to approaching aircraft; no flights cancelled.",
          "source": "Bright Defense / Financial Express",
          "url": "https://www.brightdefense.com/resources/recent-data-breaches/",
          "date": "2026-06-20"
        },
        {
          "title": "EU Council Circulates New Aviation Security Strategy Document",
          "category": "Regulatory",
          "region": "Europe",
          "severity": "Medium",
          "summary": "Council document COM(2026)229 dated 19 Jun proposes faster classified-information sharing, cargo supply-chain hardening, and a conflict-zone risk-assessment mechanism with EASA/EEAS.",
          "source": "Council of the European Union",
          "url": "https://data.consilium.europa.eu/doc/document/ST-10901-2026-INIT/en/pdf",
          "date": "2026-06-19"
        },
        {
          "title": "FAA Publishes NPRM for Drone Flight Restrictions Over Critical Infrastructure",
          "category": "Regulatory",
          "region": "North America",
          "severity": "Medium",
          "summary": "FAA published long-awaited Section 2209 NPRM on 6 May 2026 to allow facility operators to apply for UAS flight restrictions; public comments due 6 July 2026.",
          "source": "Holland & Knight / Federal Register",
          "url": "https://www.hklaw.com/en/insights/publications/2026/05/citing-national-security-needs-the-fcc-and-faa-take-steps-on-uas",
          "date": "2026-05-06"
        },
        {
          "title": "FAA Reports 100+ Monthly Drone Incursions Near Airports Amid World Cup Security Pressure",
          "category": "Threat",
          "region": "North America",
          "severity": "Medium",
          "summary": "FAA receives over 100 monthly drone sighting reports near airports; experts warn counter-UAS readiness remains uneven across federal, state and local agencies ahead of FIFA World Cup.",
          "source": "Federal News Network",
          "url": "https://federalnewsnetwork.com/commentary/2026/05/drone-threats-are-escalating-americas-airspace-intelligence-isnt-keeping-pace/",
          "date": "2026-05-07"
        },
        {
          "title": "Korean Air Data Breach Exposes 30,000 Employee Records via Oracle EBS Campaign",
          "category": "Incident",
          "region": "Asia-Pacific",
          "severity": "Medium",
          "summary": "Hackers exploited Oracle EBS zero-days to steal Korean Air employee names and bank details from catering subsidiary KC&D; Envoy Air also confirmed victim of same campaign.",
          "source": "SecurityWeek",
          "url": "https://www.securityweek.com/korean-air-data-compromised-in-oracle-ebs-hack/",
          "date": "2025-12-30"
        }
      ]
    },
    {
      "date": "2026-06-27",
      "briefing": "Globally, aviation security in the last 72 hours has been marked by significant incidents including a near-miss drone collision with a commercial airliner in North America and high-value smuggling operations in Asia-Pacific, alongside key regulatory developments from the FAA and EASA. Cyber threats and enhanced screening technologies continue to shape the evolving security landscape.",
      "items": [
        {
          "title": "Drone Nearly Collides with United Airlines Jet at Newark Airport",
          "category": "Incident",
          "region": "North America",
          "severity": "High",
          "summary": "A United Airlines Boeing 737 narrowly avoided a collision with a drone during landing approach at Newark Liberty International Airport, New Jersey.",
          "fullContent": "On Friday, June 26, 2026, a United Airlines Boeing 737, carrying 106 passengers and 5 crew members from Key West, Florida, experienced a near-collision with a drone while on final approach to Newark Liberty International Airport (EWR) in New Jersey. The pilot reported the cylindrical drone, approximately three feet wide, passed about 100 feet below the aircraft as it was coming in to land around 5:30 p.m.. Air traffic control (ATC) audio, later verified by CNN, captured the pilot's urgent report stating, \"We almost hit a drone\". Around the same time, another pilot operating a United Express flight for GoJet Airlines into Newark also reported a drone sighting at roughly 2,000 feet. The Federal Aviation Administration (FAA) prohibits drone use in controlled airspaces or near manned aircraft without official permission, noting that approximately 100 drone sightings occur near U.S. airports monthly. Despite the close encounter, the Boeing 737 landed safely, and passengers exited without incident. This event underscores the persistent and growing threat posed by unauthorized drone activity to civil aviation safety, particularly around busy airport environments, and highlights the challenges faced by air traffic control and pilots in mitigating such risks. CNN reportedly reached out to the FAA, GoJet, and Newark Airport for further information regarding the incident.",
          "source": "KRDO, CNN Newssource",
          "url": "https://vertexaisearch.cloud.google.com/grounding-api-redirect/AUZIYQE2Rw8qS_U4XGnXKJX8Ex0ETES0h1TUpnLp5jzNNL9cMKzc1GCt77WJmQCgj8iUkvmcRyGcemz_DwMc2qDgnuaSvBEi9ZvGIYdsPjLEdlT8d679kIytS5dHWXawEkq4wD0pAMVfBGGwspfuiKB5lO4mP_1Wb4kDISlcYtgkr1xsinRQeZYHRG3iMYM7qSirAwujq7p-pPLRkQ==",
          "date": "2026-06-26"
        },
        {
          "title": "Malaysian Customs Intercept $13 Million AI Chip Smuggling Attempt at Kuala Lumpur Airport",
          "category": "Incident",
          "region": "Asia-Pacific",
          "severity": "High",
          "summary": "Malaysian authorities foiled a $13 million bid to smuggle 72 advanced AI servers through Kuala Lumpur International Airport's free trade zone.",
          "fullContent": "On Friday, June 26, 2026, Malaysian customs officials announced the successful interception of an attempt to smuggle advanced Artificial Intelligence (AI) chips, valued at nearly $13 million (approximately RM 61.2 million), through the Kuala Lumpur International Airport (KLIA). The operation involved a raid on June 5 within KLIA's free trade zone, where a team seized 72 servers that were reportedly destined for export to another Asian country. According to airport customs director Zulkifli Muhammad, the servers were deliberately declared as \"computer components\" to evade detection by authorities. The syndicate behind the operation allegedly used Malaysia as a transit point to circumvent existing export restrictions. This incident highlights a growing concern following Malaysia's tightening of export and transshipment controls on chips originating from the United States last year. These controls necessitate a strategic trade permit and advance notification if there is suspicion of misuse or diversion. As Malaysia increasingly positions itself as a data-center hub, the nation is actively working to prevent its territory from being exploited as a transit route for restricted chips heading to other destinations, particularly in the context of the U.S. tightening restrictions on advanced semiconductors to curb their diversion to China. Zulkifli Muhammad did not disclose the precise origin of the servers or chips, nor their ultimate destination, stating that investigations are ongoing. A local logistics company involved in the shipment has been asked to assist with the inquiry. Malaysia has been actively probing several such cases, including one where U.S.-made Nvidia chips, originally bound for Singapore, were found in Malaysia.",
          "source": "The Peninsula Qatar, AFP",
          "url": "https://vertexaisearch.cloud.google.com/grounding-api-redirect/AUZIYQFb_AZnkCezFb9ruefOlQWz2qdgh0eZhx3lT6-Fs7c39EQf3OOV_bAZlWQ05qk49rA3QrZVA-vFyC8vH5V0hNJaV80cihuT194sMFTePqyteB6q9sI4WWIKrL3ZAYlnMF9Idm1o_s7clxW4Hf8s835iHW8H16LtV22FdBJVrVv9yQXW2d3vG5GODdlgrvCM7tnUiUxB51jpiuC8SwugG1PpRLKqYfE=",
          "date": "2026-06-26"
        },
        {
          "title": "FAA Proposes Sweeping Reforms to Modernize Aircraft Certification, Align with EASA",
          "category": "Regulatory",
          "region": "North America",
          "severity": "Medium",
          "summary": "The FAA proposed significant rule changes to streamline aircraft certification, aiming to align U.S. standards with European regulations, reducing costs and time.",
          "fullContent": "On Thursday, June 25, 2026, the U.S. Federal Aviation Administration (FAA) published a Notice of Proposed Rulemaking (NPRM) to amend various airworthiness regulations, aiming to modernize and accelerate the certification process for transport category airplanes and propulsion systems. The proposal, officially docketed as FAA-2026-0430, seeks to reduce the number of exemptions, special conditions, and equivalent level of safety findings currently required, which are often necessary when existing rules do not precisely fit new designs. This initiative is expected to reduce certification costs and time for both industry and the FAA, while maintaining or enhancing safety levels. A key aspect of the proposed changes is to align U.S. regulations more closely with those of the European Union Aviation Safety Agency (EASA). By mirroring certain EASA requirements, manufacturers like Boeing, Airbus, Embraer, and Bombardier would benefit from more consistent international regulations, thereby lowering costs and complexity in the global certification process. The FAA Administrator, Bryan Bedford, has advocated for these reforms, with the agency having several projects underway to streamline the process. The proposed changes also include moving aspects of Special Federal Aviation Regulation (SFAR) No. 109 from Part 25 into new sections, and updating rules for cabin systems, emergency exits, fire protection, and medical stretchers. Public comments on the NPRM are invited until August 25, 2026. This move reinforces the commitment of both the FAA and EASA to closer cooperation on safety and certification, especially as both agencies are progressing towards approving new Boeing 737 MAX variants.",
          "source": "Federal Register, IndexBox, AVweb, 102.7 WBOW, Air Data News",
          "url": "https://vertexaisearch.cloud.google.com/grounding-api-redirect/AUZIYQGawHG6DlGJPXz9STbDQCrAMr2QfpbFgFEiIn5a-u0w9wuDdIP6tAL_L6NqTxF3T3eIZ87j7st5-LXISA6qw2P47gGZBSthgLpfP38SuNYeGEpQJGTtsBz_GKHYJYsCAFIj5oi34xKkPrrdRNnrBQoeVM0rSrCjzvbPDAp-B1soDwDWD5Ip9ELtz6uCmamuHSKoUvYKwmyq2114A1VFU-_-tXYbjy5ewiZ2wp-DSui8RpmWXkQlS9rf",
          "date": "2026-06-25"
        },
        {
          "title": "Malaysian Authorities Foil Multiple Drug Smuggling Attempts at Kuala Lumpur International Airport",
          "category": "Incident",
          "region": "Asia-Pacific",
          "severity": "High",
          "summary": "Malaysian police disrupted three drug smuggling operations at KLIA and surrounding areas, seizing 171.6 kg of marijuana worth RM13.73 million.",
          "fullContent": "On Thursday, June 25, 2026, Selangor police chief Comm Datuk Shazeli Kahar announced the successful disruption of three separate attempts to smuggle large quantities of drugs out of Malaysia, primarily through the Kuala Lumpur International Airport (KLIA). These operations, conducted between June 17 and June 22, led to the arrest of four suspects, including one local. The first incident occurred on June 17 at KLIA's Terminal One, where luggage scanning flagged suspicious bags, resulting in the arrest of a foreigner in his 30s. Police found 29.6 kg of suspected marijuana buds, estimated to be worth around RM2.37 million (approximately $500,000 USD). A second major bust on June 18 saw Sepang and Nilai police arrest two men outside a hotel in Bandar Baru Enstek, Negri Sembilan, seizing approximately 36 kg of suspected marijuana. Further investigation led to the discovery of an additional 72 kg of marijuana at a house in Banting, bringing the total value from this operation to about RM8.64 million (approximately $1.8 million USD). The third case, on June 22, again at KLIA, involved the detention of a European man after scans revealed suspicious packages in his two pieces of luggage, containing approximately 34 kg of marijuana buds valued at RM2.72 million (approximately $575,000 USD). In total, police confiscated 171.6 kg of suspected marijuana buds with an estimated market value of RM13.73 million (approximately $2.9 million USD). All arrested suspects reportedly had no prior police records. Authorities believe the drugs were sourced from neighboring countries and intended for distribution, particularly to Europe. This year alone, from January to June, 653.6 kg of marijuana buds have been seized from KLIA, with 38 suspects arrested and 28 charged in court, highlighting a persistent challenge in aviation security for the region.",
          "source": "The Star",
          "url": "https://vertexaisearch.cloud.google.com/grounding-api-redirect/AUZIYQF2rSFgbyM6PGfegn3EhG_R3Tl0--qCYKgGA4j0bgQlhuVp3YB3tQJTRG1WMjzOL0geFb8JiYJVR2RiE5TFRV3osjtdcRfY3r99blpwfqDCNzYSlfnrfjeHdi-Odeh6uDmTzJCxWIWn_LZKVsL_WANWXl3b0YZOLNE47ZcrNeS4p-A9wTOs7cfCEdNvUko8_TY=",
          "date": "2026-06-25"
        },
        {
          "title": "EASA Extends Middle East Conflict Zone Information Bulletin Amid Ongoing Tensions",
          "category": "Regulatory",
          "region": "Middle East",
          "severity": "Medium",
          "summary": "EASA has extended its Conflict Zone Information Bulletin until July 1, advising airlines to avoid Iranian, Iraqi, and Lebanese airspace.",
          "fullContent": "On June 24, 2026, the European Union Aviation Safety Agency (EASA) announced the extension of its Conflict Zone Information Bulletin until July 1, 2026. This updated warning continues to advise airlines to avoid the airspace over Iran, Iraq, and Lebanon, and to exercise the highest degree of caution across the broader Middle East region. The decision comes despite a recently established framework understanding between the United States and Iran aimed at de-escalating tensions. EASA's assessment is based on the persistent possibility of short-term violations of any ceasefire agreements, particularly around the Strait of Hormuz and adjacent airspaces, which continue to present operational and security risks to civil aviation traffic. The ongoing geopolitical instability in the region necessitates continued vigilance and proactive measures to ensure the safety of international flights. The bulletin serves as a critical advisory for European and international carriers, guiding their flight path decisions to mitigate potential threats arising from military activities or unforeseen escalations in contested airspaces. Such directives are crucial for maintaining aviation security standards in volatile areas, emphasizing that even with diplomatic efforts, tangible reductions in operational risk for civil aviation must be clearly observed before advisories are relaxed.",
          "source": "APP.com.pk (via BRUSSELS - The European Union Aviation Safety Agency (EASA))",
          "url": "https://vertexaisearch.cloud.google.com/grounding-api-redirect/AUZIYQG-jY9Xf3llrzheoUsDcZmyvn-2RMVI7F-AqFtT-FryHS_qB0OfreFJPyQKxoGo13P1De50AP0SL0smHOwBN2H0XF8ZlVaNsFN4n44ssUrLhVEoqNrld3Usa1ycqW64Ui3vJ9l0hI6ecC8P2blSdcj0zysjNUCzFyCEroVFDOqaq5t0N9Rru8DzV9doxP-4PwWyD3AgeN8wN0DqQSjb2pdtXWQTStSZlWCt1OLsmLI=",
          "date": "2026-06-24"
        },
        {
          "title": "TSA Launches New PreCheck Touchless ID Option with Google Wallet Integration",
          "category": "Technology",
          "region": "North America",
          "severity": "Low",
          "summary": "The TSA, in collaboration with Google Wallet, introduced a new opt-in Touchless ID experience for TSA PreCheck passengers at select U.S. airports.",
          "fullContent": "On June 24, 2026, the Transportation Security Administration (TSA) announced a new opt-in experience for TSA PreCheck passengers, enabling a Touchless ID system through Google Wallet integration. This initiative aims to streamline the identity verification process at security checkpoints, enhancing efficiency and reducing physical contact. The new system allows eligible travelers to utilize their digital IDs stored in Google Wallet, which is accepted at over 50 U.S. airports. This technological advancement is part of a broader push by the TSA to modernize security screening processes, which also includes the deployment of advanced computed tomography (CT) scanners that create 3D images of bags, potentially allowing passengers to keep liquids and laptops inside their carry-ons at participating airports. While facial recognition technology is also expanding at international arrival facilities, passengers retain the option to opt-out and request a manual ID check, though this may increase processing time. The Touchless ID system, along with other innovations like AutoCAT eGates being tested at airports such as Charlotte Douglas, Los Angeles International, and Ronald Reagan Washington National, represents a significant step towards improving passenger flow and security effectiveness, particularly as the agency prepares for high travel volumes, such as the upcoming Fourth of July holiday weekend where nearly 18.7 million travelers are anticipated. The collaboration with Google Wallet specifically expands the digital ID options available to travelers, offering another convenient method for expedited security screening for those enrolled in trusted traveler programs.",
          "source": "TSA, CTV News, LegalShield, YouTube",
          "url": "https://vertexaisearch.cloud.google.com/grounding-api-redirect/AUZIYQHCsC99H0Nj6NWJGau3jXzZInuzbgC5qpcAo2KpmSXxBhLdMjDjcn_NLWvHo9yK8tI2SJK3scMD9cC_XmmS_uhJOkwamJWth17abBlDR7u5tTQIbQ==",
          "date": "2026-06-24"
        }
      ]
    }
  ],
  "lastProvider": "Gemini (2.5 Flash)"
}